{"errors":[],"warnings":[],"namedChunkGroups":{"polyfill":{"chunks":[3,0,8],"assets":["webpack-runtime-69ee0c3cc6ad3f8d65e9.js","webpack-runtime-69ee0c3cc6ad3f8d65e9.js.map","commons-bd0c3c33546f7c89f7fb.js","commons-bd0c3c33546f7c89f7fb.js.map","polyfill-b3cdf4efa4860a9f5b07.js","polyfill-b3cdf4efa4860a9f5b07.js.map"],"children":{},"childAssets":{}},"app":{"chunks":[3,7,4],"assets":["webpack-runtime-69ee0c3cc6ad3f8d65e9.js","webpack-runtime-69ee0c3cc6ad3f8d65e9.js.map","framework-83e11af5cf111be5ad89.js","framework-83e11af5cf111be5ad89.js.map","app-a8f803915a5f80a3f740.js","app-a8f803915a5f80a3f740.js.map"],"children":{},"childAssets":{}},"component---src-pages-404-js":{"chunks":[2,1,0,5],"assets":["styles.d8859fc7c5871b366045.css","styles-7d4153d260c0197f0043.js","styles-7d4153d260c0197f0043.js.map","1bfc9850-919a8cdfab81606227aa.js","1bfc9850-919a8cdfab81606227aa.js.map","commons-bd0c3c33546f7c89f7fb.js","commons-bd0c3c33546f7c89f7fb.js.map","component---src-pages-404-js-30887e448e0e82d2511a.js","component---src-pages-404-js-30887e448e0e82d2511a.js.map"],"children":{},"childAssets":{}},"component---src-pages-index-js":{"chunks":[2,1,0,6],"assets":["styles.d8859fc7c5871b366045.css","styles-7d4153d260c0197f0043.js","styles-7d4153d260c0197f0043.js.map","1bfc9850-919a8cdfab81606227aa.js","1bfc9850-919a8cdfab81606227aa.js.map","commons-bd0c3c33546f7c89f7fb.js","commons-bd0c3c33546f7c89f7fb.js.map","component---src-pages-index-js-048f74e3ccd4d75fe2c9.js","component---src-pages-index-js-048f74e3ccd4d75fe2c9.js.map"],"children":{},"childAssets":{}}},"assetsByChunkName":{"polyfill":["webpack-runtime-69ee0c3cc6ad3f8d65e9.js","commons-bd0c3c33546f7c89f7fb.js","polyfill-b3cdf4efa4860a9f5b07.js"],"app":["webpack-runtime-69ee0c3cc6ad3f8d65e9.js","framework-83e11af5cf111be5ad89.js","app-a8f803915a5f80a3f740.js"],"component---src-pages-404-js":["styles.d8859fc7c5871b366045.css","styles-7d4153d260c0197f0043.js","1bfc9850-919a8cdfab81606227aa.js","commons-bd0c3c33546f7c89f7fb.js","component---src-pages-404-js-30887e448e0e82d2511a.js"],"component---src-pages-index-js":["styles.d8859fc7c5871b366045.css","styles-7d4153d260c0197f0043.js","1bfc9850-919a8cdfab81606227aa.js","commons-bd0c3c33546f7c89f7fb.js","component---src-pages-index-js-048f74e3ccd4d75fe2c9.js"]}}